[
	{"drawDate": "06-01-2025", "one" : "34*16", "two" : "33*32", "three" : "06*08"},
	{"drawDate": "06-02-2025", "one" : "28*28", "two" : "02*26", "three" : "25*09"},
	{"drawDate": "06-03-2025", "one" : "37*24", "two" : "11*34", "three" : "26*19"},
	{"drawDate": "06-04-2025", "one" : "18*27", "two" : "05*28", "three" : "11*11"},
	{"drawDate": "06-05-2025", "one" : "07*15", "two" : "14*33", "three" : "28*06"},
	{"drawDate": "06-06-2025", "one" : "02*31", "two" : "07*25", "three" : "30*02"},
	{"drawDate": "06-07-2025", "one" : "26*37", "two" : "23*17", "three" : "38*12"},
	{"drawDate": "06-08-2025", "one" : "17*05", "two" : "07*03", "three" : "23*10"},
	{"drawDate": "06-09-2025", "one" : "29*14", "two" : "29*11", "three" : "24*15"},
	{"drawDate": "06-10-2025", "one" : "38*21", "two" : "05*20", "three" : "26*01"},
	{"drawDate": "06-11-2025", "one" : "37*03", "two" : "04*15", "three" : "01*20"},
	{"drawDate": "06-12-2025", "one" : "28*08", "two" : "28*15", "three" : "06*27"},
	{"drawDate": "06-13-2025", "one" : "08*25", "two" : "15*22", "three" : "30*14"},
	{"drawDate": "06-14-2025", "one" : "03*21", "two" : "20*33", "three" : "12*34"},
	{"drawDate": "06-15-2025", "one" : "03*32", "two" : "06*22", "three" : "36*18"},
	{"drawDate": "06-16-2025", "one" : "35*10", "two" : "35*08", "three" : "37*29"},
	{"drawDate": "06-17-2025", "one" : "22*05", "two" : "27*31", "three" : ""}
]
